OpenPS/__init__.py
OpenPS/event.py
OpenPS-1.1.0.dist-info/LICENSE
OpenPS-1.1.0.dist-info/METADATA
OpenPS-1.1.0.dist-info/WHEEL
OpenPS-1.1.0.dist-info/dependency_links.txt
OpenPS-1.1.0.dist-info/top_level.txt
OpenPS-1.1.0.dist-info/RECORD
