Metadata-Version: 2.1
Name: OpenPS
Version: 1.1.0
Summary: Open source plugin system.
Home-page: UNKNOWN
Author: TheKruger
License: Apache-2.0
Keywords: python,plugin-system
Platform: UNKNOWN
